minetorch/__init__.py
minetorch/command_line.py
minetorch/drawers.py
minetorch/metrics.py
minetorch/miner.py
minetorch/plugin.py
minetorch/spreadsheet.py
minetorch/statable.py
minetorch/utils.py
minetorch/plugins/__init__.py
minetorch/plugins/noise_detector.py
Minetorch-0.6.7.dist-info/LICENSE
Minetorch-0.6.7.dist-info/METADATA
Minetorch-0.6.7.dist-info/WHEEL
Minetorch-0.6.7.dist-info/entry_points.txt
Minetorch-0.6.7.dist-info/top_level.txt
Minetorch-0.6.7.dist-info/RECORD
